setup.py
hakhakhak/__init__.py
hakhakhak/listsort.py
hakhakhak.egg-info/PKG-INFO
hakhakhak.egg-info/SOURCES.txt
hakhakhak.egg-info/dependency_links.txt
hakhakhak.egg-info/requires.txt
hakhakhak.egg-info/top_level.txt